Metadata-Version: 1.1
Name: Kadot
Version: 0.1.9
Summary: Kadot, unsupervised natural language processing.
Home-page: https://github.com/the-new-sky/Kadot
Author: the_new_sky
Author-email: lorisazerty@gmail.com
License: MIT
Download-URL: https://github.com/the-new-sky/Kadot/archive/0.1.9.tar.gz
Keywords: natural language processing,text classification,text generation,tokenizer,word embeddings
Platform: UNKNOWN
Classifier: Development Status :: 3 - Alpha
Classifier: Intended Audience :: Developers
Classifier: License :: OSI Approved :: MIT License
Classifier: Programming Language :: Python :: 3.5
Classifier: Programming Language :: Python :: 3.6
Classifier: Topic :: Scientific/Engineering :: Artificial Intelligence
Classifier: Topic :: Text Processing :: General
